{"OP1": {"profile_text": "    time       1.2% fanout         1 input         1 rows\n      clear: (<V set_ctr$83 in>)\n    s# 86 84 cluster outer seq start, set no <V set_ctr$83 in>    \n    save ctx:()\n      clear: (<V mealTotal$29 an>, <V description$28 a>, <V set_no$30 i>, <V mealTotal$75 a>, <V description$73 a>)\n    s# 95 27 Subquery 27 \n      multistate set no = <V set_no$30 i>\n      { ", "profile_text_low_explain": "\n    time       1.5% fanout         1 input         1 rows\n    Subquery 27 \n      { ", "time": 1.2, "fanout": 1.0, "input_rows": 1.0, "cardinality_estimate": 0, "cardinality_fanout": 0, "operator_type": 0, "precode_bool": 0, "after_code_bool": 0, "group_by_read": 0, "distinct_bool": 0, "TOP_bool": 0, "TOP_num": 0, "top_order_by_bool": 0, "skip_node_bool": 0, "skip_node_num": 0, "{": 1, "}": 0, "select?": 0, "start_optional": 0, "end_optional": 0, "IRI_ID\"...amount\"": 0, "IRI_ID\"...description\"": 0, "optional_section?": 0, "after_test_1op?": 0, "after_test_lvl": 0, "target_bracket": 0, "transitive_bracket": 0, "union_sort_lvl": 0, "sort_lvl": 0, "subquerie_lvl": 1, "union_sub_lvl": 0, "subquery_select?": 0}, "OP2": {"profile_text": "        time        14% fanout         1 input         1 rows\n        \n        s# 129 38 Fork 38 {  \n                \n            save ctx:()\n              set no = <V set_no$30 i> array  <none>  save: ", "profile_text_low_explain": "\n        time        16% fanout         1 input         1 rows\n        fork {", "time": 14.0, "fanout": 1.0, "input_rows": 1.0, "cardinality_estimate": 0, "cardinality_fanout": 0, "operator_type": 0, "precode_bool": 0, "after_code_bool": 0, "group_by_read": 0, "distinct_bool": 0, "TOP_bool": 0, "TOP_num": 0, "top_order_by_bool": 0, "skip_node_bool": 0, "skip_node_num": 0, "{": 1, "}": 0, "select?": 0, "start_optional": 0, "end_optional": 0, "IRI_ID\"...amount\"": 0, "IRI_ID\"...description\"": 0, "optional_section?": 0, "after_test_1op?": 0, "after_test_lvl": 0, "target_bracket": 0, "transitive_bracket": 0, "sort_lvl": 1, "union_sort_lvl": 0, "subquerie_lvl": 1, "union_sub_lvl": 0, "subquery_select?": 0}, "OP3": {"profile_text": "            time        18% fanout         9 input         1 rows\n              clear: (<V s_11_4_t1.O$32 an>, <V s_11_4_t1.S$33 rn>)\n              clear on continue: (<V s_11_4_t1.O$32 an>, <V s_11_4_t1.S$33 rn>)\n            s# 100 31 from DB.DBA.RDF_QUAD by RDF_QUAD          9 rows Parallel, tail cost        17   \n            Key RDF_QUAD  ASC  (<V s_11_4_t1.S$33 rn>, <V s_11_4_t1.O$32 an>)\n             inlined  P =  IRI_ID\"...amount\" \n            copy on branch $30 $0 $0 $0 sets: 86 \n            ", "profile_text_low_explain": "\n            time        22% fanout         9 input         1 rows\n            RDF_QUAD         9 rows(s_11_4_t1.S$33, s_11_4_t1.O$32)\n             inlined  P =  IRI_ID\"...amount\" ", "time": 18.0, "fanout": 9.0, "input_rows": 1.0, "cardinality_estimate": 0, "cardinality_fanout": 0, "operator_type": 1, "precode_bool": 0, "after_code_bool": 0, "group_by_read": 0, "distinct_bool": 0, "P": "IRI_ID\"...amount\"", "P_math_op": "=", "TOP_bool": 0, "TOP_num": 0, "top_order_by_bool": 0, "skip_node_bool": 0, "skip_node_num": 0, "{": 0, "}": 0, "select?": 0, "start_optional": 0, "end_optional": 0, "IRI_ID\"...amount\"": 1, "IRI_ID\"...description\"": 0, "optional_section?": 0, "after_test_1op?": 0, "after_test_lvl": 0, "target_bracket": 0, "transitive_bracket": 0, "union_sort_lvl": 0, "sort_lvl": 1, "subquerie_lvl": 1, "union_sub_lvl": 0, "subquery_select?": 0}, "OP4": {"profile_text": "            time        20% fanout         1 input         9 rows\n              clear: (<V s_11_4_t0.O$36 an>)\n              clear on continue: (<V s_11_4_t0.O$36 an>)$33 () \n            s# 111 35 from DB.DBA.RDF_QUAD by RDF_QUAD          1 rows Parallel, tail cost       1.2   \n            Key RDF_QUAD  ASC  (<V s_11_4_t0.O$36 an>)\n             inlined  P =  IRI_ID\"...description\"  ,  S = <V s_11_4_t1.S$33 rn>\n            copy on branch $33 $30 $32 $0 sets: 86 100 \n            ", "profile_text_low_explain": "\n            time        11% fanout         1 input         9 rows\n            RDF_QUAD         1 rows(s_11_4_t0.O$36)\n             inlined  P =  IRI_ID\"...description\"  ,  S = s_11_4_t1.S$33", "time": 20.0, "fanout": 1.0, "input_rows": 9.0, "cardinality_estimate": 0, "cardinality_fanout": 0, "operator_type": 1, "precode_bool": 0, "after_code_bool": 0, "group_by_read": 0, "distinct_bool": 0, "P": "IRI_ID\"...description\"", "P_math_op": "=", "S": "s_11_4_t1.S", "S_math_op": "=", "TOP_bool": 0, "TOP_num": 0, "top_order_by_bool": 0, "skip_node_bool": 0, "skip_node_num": 0, "{": 0, "}": 0, "select?": 0, "start_optional": 0, "end_optional": 0, "IRI_ID\"...amount\"": 0, "IRI_ID\"...description\"": 1, "optional_section?": 0, "after_test_1op?": 0, "after_test_lvl": 0, "target_bracket": 0, "transitive_bracket": 0, "union_sort_lvl": 0, "sort_lvl": 1, "subquerie_lvl": 1, "union_sub_lvl": 0, "subquery_select?": 0}, "OP5": {"profile_text": "            time        15% fanout         0 input         9 rows\n            $32 (35 ) \n            s# 121 39 Sort (HASH) set no <r set_no$30 via  Set111 Set100>(<V s_11_4_t0.O$36 an>) -> (<r s_11_4_t1.O$32 via  Set111>) up to         3 distinct\n            \n        }", "profile_text_low_explain": "\n            time        18% fanout         0 input         9 rows\n            Sort (s_11_4_t0.O$36) -> (s_11_4_t1.O$32)\n            \n          }", "time": 15.0, "fanout": 0.0, "input_rows": 9.0, "cardinality_estimate": 0, "cardinality_fanout": 0, "operator_type": 0, "precode_bool": 0, "after_code_bool": 0, "group_by_read": 0, "distinct_bool": 1, "TOP_bool": 0, "TOP_num": 0, "top_order_by_bool": 0, "skip_node_bool": 0, "skip_node_num": 0, "{": 0, "}": 1, "select?": 0, "start_optional": 0, "end_optional": 0, "IRI_ID\"...amount\"": 0, "IRI_ID\"...description\"": 0, "optional_section?": 0, "after_test_1op?": 0, "after_test_lvl": 0, "target_bracket": 0, "transitive_bracket": 0, "sort_lvl": 1, "union_sort_lvl": 0, "subquerie_lvl": 1, "union_sub_lvl": 0, "subquery_select?": 0}, "OP6": {"profile_text": "        time        31% fanout         3 input         1 rows\n          clear: (<V aggregate$40 an>, <V s_11_4_t0.O$36 an>, <V mealTotal$29 an>, <V description$28 a>, <V __ro2sq$64 a>)\n          clear on continue: (<V aggregate$40 an>, <V s_11_4_t0.O$36 an>, <V mealTotal$29 an>, <V description$28 a>, <V __ro2sq$64 a>)\n        s# 136 46 group by read node  \n        (<V s_11_4_t0.O$36 an>, <V aggregate$40 an>)\n        After code:\n          0: <V __ro2sq$64 a> := Call __ro2sq (<V s_11_4_t0.O$36 an>)\n          5: <V description$28 a> :=  := artm <V __ro2sq$64 a>\n          9: <V mealTotal$29 an> :=  := artm <V aggregate$40 an>\n          13: BReturn 0", "profile_text_low_explain": "\n        time        31% fanout         3 input         1 rows\n        group by read node  \n        (s_11_4_t0.O$36, aggregate$40)\n        \n        After code:\n        0: __ro2sq$64 := Call __ro2sq (s_11_4_t0.O$36)\n        5: description$28 :=  := artm __ro2sq$64\n        9: mealTotal$29 :=  := artm aggregate$40\n        13: BReturn 0", "time": 31.0, "fanout": 3.0, "input_rows": 1.0, "cardinality_estimate": 0, "cardinality_fanout": 0, "operator_type": 0, "precode_bool": 0, "after_code_bool": 1, "after_code_text": "After code:\n          0: <V __ro2sq$64 a> := Call __ro2sq (<V s_11_4_t0.O$36 an>)\n          5: <V description$28 a> :=  := artm <V __ro2sq$64 a>\n          9: <V mealTotal$29 an> :=  := artm <V aggregate$40 an>\n          13: BReturn 0", "group_by_read_bool": 1, "distinct_bool": 0, "TOP_bool": 0, "TOP_num": 0, "top_order_by_bool": 0, "skip_node_bool": 0, "skip_node_num": 0, "{": 0, "}": 0, "select?": 0, "start_optional": 0, "end_optional": 0, "IRI_ID\"...amount\"": 0, "IRI_ID\"...description\"": 0, "optional_section?": 0, "after_test_1op?": 0, "after_test_lvl": 0, "target_bracket": 0, "transitive_bracket": 0, "union_sort_lvl": 0, "sort_lvl": 0, "subquerie_lvl": 1, "union_sub_lvl": 0, "subquery_select?": 0}, "OP7": {"profile_text": "        time      0.34% fanout         0 input         3 rows\n        \n        s# 95 66 Subquery Select(<V description$28 a>, <V mealTotal$29 an>)\n          set no: <r set_no$30 via  Set136>\n      }\n    \n    After code:\n      0: <V description$73 a> := Call __ro2sq (<V description$28 a>)\n      5: <V mealTotal$75 a> := Call __ro2sq (<V mealTotal$29 an>)\n      10: BReturn 0", "profile_text_low_explain": "\n        time       0.4% fanout         0 input         3 rows\n        Subquery Select(description$28, mealTotal$29)\n      }\n    \n    After code:\n    0: description$73 := Call __ro2sq (description$28)\n    5: mealTotal$75 := Call __ro2sq (mealTotal$29)\n    10: BReturn 0", "time": 0.34, "fanout": 0.0, "input_rows": 3.0, "cardinality_estimate": 0, "cardinality_fanout": 0, "operator_type": 0, "precode_bool": 0, "after_code_bool": 1, "after_code_text": "After code:\n      0: <V description$73 a> := Call __ro2sq (<V description$28 a>)\n      5: <V mealTotal$75 a> := Call __ro2sq (<V mealTotal$29 an>)\n      10: BReturn 0", "group_by_read": 0, "distinct_bool": 0, "TOP_bool": 0, "TOP_num": 0, "top_order_by_bool": 0, "skip_node_bool": 0, "skip_node_num": 0, "{": 0, "}": 1, "select?": 0, "start_optional": 0, "end_optional": 0, "IRI_ID\"...amount\"": 0, "IRI_ID\"...description\"": 0, "optional_section?": 0, "after_test_1op?": 0, "after_test_lvl": 0, "target_bracket": 0, "transitive_bracket": 0, "union_sort_lvl": 0, "sort_lvl": 0, "subquerie_lvl": 1, "union_sub_lvl": 0, "subquery_select?": 1}, "OP8": {"profile_text": "    time      0.11% fanout         0 input         3 rows\n    $73 (27 ) $75 (27 ) $83 (27 84 ) \n    s# 155 77 Select (<V description$73 a>, <V mealTotal$75 a>)\n      set no: <r set_ctr$83 via  Set95>\n  ", "profile_text_low_explain": "\n    time      0.16% fanout         0 input         3 rows\n    Select (description$73, mealTotal$75)\n  ", "time": 0.11, "fanout": 0.0, "input_rows": 3.0, "cardinality_estimate": 0, "cardinality_fanout": 0, "operator_type": 0, "precode_bool": 0, "after_code_bool": 0, "group_by_read": 0, "distinct_bool": 0, "TOP_bool": 0, "TOP_num": 0, "top_order_by_bool": 0, "skip_node_bool": 0, "skip_node_num": 0, "{": 0, "}": 0, "select?": 1, "start_optional": 0, "end_optional": 0, "IRI_ID\"...amount\"": 0, "IRI_ID\"...description\"": 0, "optional_section?": 0, "after_test_1op?": 0, "after_test_lvl": 0, "target_bracket": 0, "transitive_bracket": 0, "union_sort_lvl": 0, "sort_lvl": 0, "subquerie_lvl": 0, "union_sub_lvl": 0, "subquery_select?": 0}}