{"OP1": {"profile_text": "    time       6.9% fanout         1 input         1 rows\n      clear: (<V set_ctr$176 in>)\n    s# 179 177 cluster outer seq start, set no <V set_ctr$176 in>    \n    save ctx:()\n    Precode:\n      0: <V __all_eq$27 x> := Call __all_eq ( IRI_ID\"...Q515\" )\n      5: BReturn 0\n      clear: (<V var1$30 a>, <V set_no$31 i>, <V __all_eq$27 x>, <V var1$168 a>)\n    s# 188 29 Subquery 29 \n      multistate set no = <V set_no$31 i>\n      { \n        \n        s# 192 32 Union\n          { ", "profile_text_low_explain": "\n    time       5.2% fanout         1 input         1 rows\n    Precode:\n      0: __all_eq$27 := Call __all_eq ( IRI_ID\"...Q515\" )\n      5: BReturn 0\n    Subquery 29 \n      { \n        Union\n          { ", "time": 6.9, "fanout": 1.0, "input_rows": 1.0, "cardinality_estimate": 0, "cardinality_fanout": 0, "operator_type": 0, "precode_bool": 1, "precode_text": "Precode:\n      0: <V __all_eq$27 x> := Call __all_eq ( IRI_ID\"...Q515\" )\n      5: BReturn 0", "after_code_bool": 0, "group_by_read_bool": 0, "distinct_bool": 0, "TOP_bool": 0, "TOP_num": 0, "top_order_by_bool": 0, "skip_node_bool": 0, "skip_node_num": 0, "{": 2, "}": 0, "select?": 0, "start_optional": 0, "end_optional": 0, "IRI_ID\"...direct/P6\"": 0, "IRI_ID\"...direct/P279\"": 0, "IRI_ID\"...direct/P31\"": 0, "optional_section?": 0, "after_test_1op?": 0, "after_test_lvl": 0, "target_bracket": 0, "transitive_bracket": 0, "union_sort_lvl": 0, "sort_lvl": 0, "subquerie_lvl": 1, "union_sub_lvl": 1, "subquery_select?": 0}, "OP2": {"profile_text": "            time        63% fanout         0 input         1 rows\n            Warning: the cardinality estimate of the cost model differs greatly from the measured time. Cardinality estimate:       0.3 Fanout:         0\n              clear: (<V s_37_15_t2.O$34 an>)\n              clear on continue: (<V s_37_15_t2.O$34 an>)\n            s# 195 33 from DB.DBA.RDF_QUAD by RDF_QUAD        0.3 rows   \n            Key RDF_QUAD  ASC  (<V s_37_15_t2.O$34 an>)\n             inlined  P =  IRI_ID\"...direct/P6\"  ,  S =  IRI_ID\"...Q2079\" \n            ", "profile_text_low_explain": "\n            time        70% fanout         0 input         1 rows\n            Warning: the cardinality estimate of the cost model differs greatly from the measured time. Cardinality estimate:       0.3 Fanout:         0\n            RDF_QUAD       0.3 rows(s_37_15_t2.O$34)\n             inlined  P =  IRI_ID\"...direct/P6\"  ,  S =  IRI_ID\"...Q2079\" ", "time": 63.0, "fanout": 0.0, "input_rows": 1.0, "cardinality_estimate": 0.3, "cardinality_fanout": 0.0, "operator_type": 1, "precode_bool": 0, "after_code_bool": 0, "group_by_read_bool": 0, "distinct_bool": 0, "P": "IRI_ID\"...direct/P6\"", "P_math_op": "=", "S": "IRI_ID\"...Q2079\"", "S_math_op": "=", "TOP_bool": 0, "TOP_num": 0, "top_order_by_bool": 0, "skip_node_bool": 0, "skip_node_num": 0, "{": 0, "}": 0, "select?": 0, "start_optional": 0, "end_optional": 0, "IRI_ID\"...direct/P6\"": 1, "IRI_ID\"...direct/P279\"": 0, "IRI_ID\"...direct/P31\"": 0, "optional_section?": 0, "after_test_1op?": 0, "after_test_lvl": 0, "target_bracket": 0, "transitive_bracket": 0, "union_sort_lvl": 0, "sort_lvl": 0, "subquerie_lvl": 1, "union_sub_lvl": 1, "subquery_select?": 0}, "OP3": {"profile_text": "            time         0% fanout         0 input         0 rows\n            Warning: the cardinality estimate of the cost model differs greatly from the measured time. Cardinality estimate:       0.3 Fanout:         0\n              clear: (<V s_37_3_t0.O$37 an>)\n              clear on continue: (<V s_37_3_t0.O$37 an>)\n            s# 205 36 from DB.DBA.RDF_QUAD by RDF_QUAD        0.3 rows   \n            Key RDF_QUAD  ASC  (<V s_37_3_t0.O$37 an>)\n             inlined  P =  IRI_ID\"...direct/P31\"  ,  S =  IRI_ID\"...Q2079\" \n            row specs:  O LIKE <c T\u00f3>\n            \n            Precode:\n              0: <V __all_eq$39 x> := Call __all_eq (<V s_37_3_t0.O$37 an>)\n              5: BReturn 0\n              clear: (<V _::trans_obj_37_6$43 an>, <V _::trans_subj_37_5$42 rn>, <V __all_eq$39 x>)\n              clear on continue: (<V _::trans_subj_37_5$42 rn>, <V _::trans_obj_37_6$43 an>)$37 () \n            s# 215 41 Transitive dt dir 2, input: (<r __all_eq$27 via  Set205 Set195>)\n              input shadow: (<V __all_eq$219 x>)\n              output: (<V _::trans_subj_37_5$42 rn>)\n             Target:  (<V __all_eq$39 x>)\n              { ", "profile_text_low_explain": "\n            time         0% fanout         0 input         0 rows\n            Warning: the cardinality estimate of the cost model differs greatly from the measured time. Cardinality estimate:       0.3 Fanout:         0\n            RDF_QUAD       0.3 rows(s_37_3_t0.O$37)\n             inlined  P =  IRI_ID\"...direct/P31\"  ,  S =  IRI_ID\"...Q2079\"  O LIKE <c T\u00f3>\n            Precode:\n              0: __all_eq$39 := Call __all_eq (s_37_3_t0.O$37)\n              5: BReturn 0\n            Transitive dt dir 2, input: (__all_eq$27)\n              input shadow: (__all_eq$219)\n              output: (_::trans_subj_37_5$42)\n             Target:  (__all_eq$39)\n              { ", "time": 0.0, "fanout": 0.0, "input_rows": 0.0, "cardinality_estimate": 0.3, "cardinality_fanout": 0.0, "operator_type": 1, "precode_bool": 1, "precode_text": "Precode:\n              0: <V __all_eq$39 x> := Call __all_eq (<V s_37_3_t0.O$37 an>)\n              5: BReturn 0", "after_code_bool": 0, "group_by_read_bool": 0, "distinct_bool": 0, "P": "IRI_ID\"...direct/P31\"", "P_math_op": "=", "S": "IRI_ID\"...Q2079\"", "S_math_op": "=", "O_rs": "T\u00f3>", "O_rs_math_op": "LIKE", "TOP_bool": 0, "TOP_num": 0, "top_order_by_bool": 0, "skip_node_bool": 0, "skip_node_num": 0, "{": 1, "}": 0, "select?": 0, "start_optional": 0, "end_optional": 0, "IRI_ID\"...direct/P6\"": 0, "IRI_ID\"...direct/P279\"": 0, "IRI_ID\"...direct/P31\"": 1, "optional_section?": 0, "after_test_1op?": 0, "after_test_lvl": 0, "target_bracket": 1, "transitive_bracket": 1, "union_sort_lvl": 0, "sort_lvl": 0, "subquerie_lvl": 1, "union_sub_lvl": 1, "subquery_select?": 0}, "OP4": {"profile_text": "                time         0% fanout         0 input         0 rows\n                Warning: the cardinality estimate of the cost model differs greatly from the measured time. Cardinality estimate:       3.8 Fanout:         0\n                  clear: (<V t4.O$48 an>, <V t4.S$49 rn>, <V _::trans_obj_37_6$43 an>, <V _::trans_subj_37_5$42 rn>)\n                  clear on continue: (<V _::trans_subj_37_5$42 rn>, <V _::trans_obj_37_6$43 an>, <V t4.S$49 rn>, <V t4.O$48 an>)$219 (47 ) $225 (47 ) \n                s# 221 47 from DB.DBA.RDF_QUAD by RDF_QUAD_POGS        3.8 rows   \n                Key RDF_QUAD_POGS  ASC  (<V t4.S$49 rn>, <V t4.O$48 an>)\n                 P =  IRI_ID\"...direct/P279\"  ,  O = <v k___all_eq$225 Set227 an>\n                vector param casts: <V __all_eq$219 x>-> <v k___all_eq$225 Set227 an>\n                \n                After code:\n                  0: <V _::trans_subj_37_5$42 rn> :=  := artm <V t4.S$49 rn>\n                  4: <V _::trans_obj_37_6$43 an> :=  := artm <V t4.O$48 an>\n                  8: BReturn 0", "profile_text_low_explain": "\n                time         0% fanout         0 input         0 rows\n                Warning: the cardinality estimate of the cost model differs greatly from the measured time. Cardinality estimate:       3.8 Fanout:         0\n                RDF_QUAD_POGS       3.8 rows(t4.S$49, t4.O$48)\n                 P =  IRI_ID\"...direct/P279\"  ,  O = k___all_eq$225\n                \n                After code:\n                0: _::trans_subj_37_5$42 :=  := artm t4.S$49\n                4: _::trans_obj_37_6$43 :=  := artm t4.O$48\n                8: BReturn 0", "time": 0.0, "fanout": 0.0, "input_rows": 0.0, "cardinality_estimate": 3.8, "cardinality_fanout": 0.0, "operator_type": 1, "precode_bool": 0, "after_code_bool": 1, "after_code_text": "After code:\n                  0: <V _::trans_subj_37_5$42 rn> :=  := artm <V t4.S$49 rn>\n                  4: <V _::trans_obj_37_6$43 an> :=  := artm <V t4.O$48 an>\n                  8: BReturn 0", "group_by_read_bool": 0, "distinct_bool": 0, "P": "IRI_ID\"...direct/P279\"", "P_math_op": "=", "O": "k___all_eq", "O_math_op": "=", "TOP_bool": 0, "TOP_num": 0, "top_order_by_bool": 0, "skip_node_bool": 0, "skip_node_num": 0, "{": 0, "}": 0, "select?": 0, "start_optional": 0, "end_optional": 0, "IRI_ID\"...direct/P6\"": 0, "IRI_ID\"...direct/P279\"": 1, "IRI_ID\"...direct/P31\"": 0, "optional_section?": 0, "after_test_1op?": 0, "after_test_lvl": 0, "target_bracket": 1, "transitive_bracket": 1, "union_sort_lvl": 0, "sort_lvl": 0, "subquerie_lvl": 1, "union_sub_lvl": 1, "subquery_select?": 0}, "OP5": {"profile_text": "                time         0% fanout         0 input         0 rows\n                \n                s# 238 51 Subquery Select(<V _::trans_subj_37_5$42 rn>, <V _::trans_obj_37_6$43 an>)\n                  set no: <r step_set$44 via  Set221 Set227>\n              }\n            Reverse transitive node, input: (<V __all_eq$39 x>)\n              output: (<V _::trans_obj_37_6$43 an>)\n             Target:  (<V __all_eq$27 x>)\n              { ", "profile_text_low_explain": "\n                time         0% fanout         0 input         0 rows\n                Subquery Select(_::trans_subj_37_5$42, _::trans_obj_37_6$43)\n              }\n            Reverse transitive node, input: (__all_eq$39)\n              output: (_::trans_obj_37_6$43)\n             Target:  (__all_eq$27)\n              { ", "time": 0.0, "fanout": 0.0, "input_rows": 0.0, "cardinality_estimate": 0, "cardinality_fanout": 0, "operator_type": 0, "precode_bool": 0, "after_code_bool": 0, "group_by_read_bool": 0, "distinct_bool": 0, "TOP_bool": 0, "TOP_num": 0, "top_order_by_bool": 0, "skip_node_bool": 0, "skip_node_num": 0, "{": 1, "}": 1, "select?": 0, "start_optional": 0, "end_optional": 0, "IRI_ID\"...direct/P6\"": 0, "IRI_ID\"...direct/P279\"": 0, "IRI_ID\"...direct/P31\"": 0, "optional_section?": 0, "after_test_1op?": 0, "after_test_lvl": 0, "target_bracket": 2, "transitive_bracket": 1, "union_sort_lvl": 0, "sort_lvl": 0, "subquerie_lvl": 1, "union_sub_lvl": 1, "subquery_select?": 1}, "OP6": {"profile_text": "                time         0% fanout         0 input         0 rows\n                Warning: the cardinality estimate of the cost model differs greatly from the measured time. Cardinality estimate:       1.4 Fanout:         0\n                  clear: (<V t4.O$73 an>, <V t4.S$74 rn>, <V _::trans_obj_37_6$43 an>, <V _::trans_subj_37_5$42 rn>)\n                  clear on continue: (<V _::trans_subj_37_5$42 rn>, <V _::trans_obj_37_6$43 an>, <V t4.S$74 rn>, <V t4.O$73 an>)$249 (72 ) $255 (72 ) \n                s# 251 72 from DB.DBA.RDF_QUAD by RDF_QUAD        1.4 rows   \n                Key RDF_QUAD  ASC  (<V t4.S$74 rn>, <V t4.O$73 an>)\n                 inlined  P =  IRI_ID\"...direct/P279\"  ,  S = <v k___all_eq$255 Set257 rn>\n                vector param casts: <V __all_eq$249 x>-> <v k___all_eq$255 Set257 rn>\n                \n                After code:\n                  0: <V _::trans_subj_37_5$42 rn> :=  := artm <V t4.S$74 rn>\n                  4: <V _::trans_obj_37_6$43 an> :=  := artm <V t4.O$73 an>\n                  8: BReturn 0", "profile_text_low_explain": "\n                time         0% fanout         0 input         0 rows\n                Warning: the cardinality estimate of the cost model differs greatly from the measured time. Cardinality estimate:       1.4 Fanout:         0\n                RDF_QUAD       1.4 rows(t4.S$74, t4.O$73)\n                 inlined  P =  IRI_ID\"...direct/P279\"  ,  S = k___all_eq$255\n                \n                After code:\n                0: _::trans_subj_37_5$42 :=  := artm t4.S$74\n                4: _::trans_obj_37_6$43 :=  := artm t4.O$73\n                8: BReturn 0", "time": 0.0, "fanout": 0.0, "input_rows": 0.0, "cardinality_estimate": 1.4, "cardinality_fanout": 0.0, "operator_type": 1, "precode_bool": 0, "after_code_bool": 1, "after_code_text": "After code:\n                  0: <V _::trans_subj_37_5$42 rn> :=  := artm <V t4.S$74 rn>\n                  4: <V _::trans_obj_37_6$43 an> :=  := artm <V t4.O$73 an>\n                  8: BReturn 0", "group_by_read_bool": 0, "distinct_bool": 0, "P": "IRI_ID\"...direct/P279\"", "P_math_op": "=", "S": "k___all_eq", "S_math_op": "=", "TOP_bool": 0, "TOP_num": 0, "top_order_by_bool": 0, "skip_node_bool": 0, "skip_node_num": 0, "{": 0, "}": 0, "select?": 0, "start_optional": 0, "end_optional": 0, "IRI_ID\"...direct/P6\"": 0, "IRI_ID\"...direct/P279\"": 1, "IRI_ID\"...direct/P31\"": 0, "optional_section?": 0, "after_test_1op?": 0, "after_test_lvl": 0, "target_bracket": 2, "transitive_bracket": 0, "union_sort_lvl": 0, "sort_lvl": 0, "subquerie_lvl": 1, "union_sub_lvl": 1, "subquery_select?": 0}, "OP7": {"profile_text": "                time         0% fanout         0 input         0 rows\n                $42 () \n                s# 266 76 Subquery Select(<V _::trans_subj_37_5$42 rn>, <V _::trans_obj_37_6$43 an>)\n                  set no: <r step_set$69 via  Set251 Set257>\n              }", "profile_text_low_explain": "\n                time         0% fanout         0 input         0 rows\n                Subquery Select(_::trans_subj_37_5$42, _::trans_obj_37_6$43)\n              }", "time": 0.0, "fanout": 0.0, "input_rows": 0.0, "cardinality_estimate": 0, "cardinality_fanout": 0, "operator_type": 0, "precode_bool": 0, "after_code_bool": 0, "group_by_read_bool": 0, "distinct_bool": 0, "TOP_bool": 0, "TOP_num": 0, "top_order_by_bool": 0, "skip_node_bool": 0, "skip_node_num": 0, "{": 0, "}": 1, "select?": 0, "start_optional": 0, "end_optional": 0, "IRI_ID\"...direct/P6\"": 0, "IRI_ID\"...direct/P279\"": 0, "IRI_ID\"...direct/P31\"": 0, "optional_section?": 0, "after_test_1op?": 0, "after_test_lvl": 0, "target_bracket": 2, "transitive_bracket": 0, "union_sort_lvl": 0, "sort_lvl": 0, "subquerie_lvl": 1, "union_sub_lvl": 1, "subquery_select?": 1}, "OP8": {"profile_text": "            time         0% fanout         0 input         0 rows\n              clear: (<V var1$30 a>)$34 (41 36 ) $43 () \n            s# 283 278 END Node\n            After test:\n              0: if (<V _::trans_obj_37_6$43 an> =  IRI_ID\"...Q515\" ) then 4 else 5 unkn 5\n              4: BReturn 1\n              5: BReturn 0\n            After code:\n              0: <V var1$30 a> :=  := artm <r s_37_15_t2.O$34 via  Set283 Set215 Set205>\n              4: BReturn 0", "profile_text_low_explain": "\n            time         0% fanout         0 input         0 rows\n            END Node\n            After test:\n            0: if (_::trans_obj_37_6$43 =  IRI_ID\"...Q515\" ) then 4 else 5 unkn 5\n            4: BReturn 1\n            5: BReturn 0\n            \n            After code:\n            0: var1$30 :=  := artm s_37_15_t2.O$34\n            4: BReturn 0", "time": 0.0, "fanout": 0.0, "input_rows": 0.0, "cardinality_estimate": 0, "cardinality_fanout": 0, "operator_type": 0, "precode_bool": 0, "after_code_bool": 1, "after_code_text": "After code:\n              0: <V var1$30 a> :=  := artm <r s_37_15_t2.O$34 via  Set283 Set215 Set205>\n              4: BReturn 0", "group_by_read_bool": 0, "distinct_bool": 0, "TOP_bool": 0, "TOP_num": 0, "top_order_by_bool": 0, "skip_node_bool": 0, "skip_node_num": 0, "{": 0, "}": 0, "select?": 0, "start_optional": 0, "end_optional": 0, "IRI_ID\"...direct/P6\"": 0, "IRI_ID\"...direct/P279\"": 0, "IRI_ID\"...direct/P31\"": 0, "optional_section?": 0, "after_test_lvl": 1, "after_test_1op?": 1, "target_bracket": 1, "transitive_bracket": 0, "union_sort_lvl": 0, "sort_lvl": 0, "subquerie_lvl": 1, "union_sub_lvl": 1, "subquery_select?": 0}, "OP9": {"profile_text": "            time         0% fanout         0 input         0 rows\n            \n            s# 188 93 Subquery Select(<V var1$30 a>)\n              set no: <r set_no$31 via  Set283 Set215 Set205 Set195>\n          }\n          { ", "profile_text_low_explain": "\n            time         0% fanout         0 input         0 rows\n            Subquery Select(var1$30)\n          }\n          { ", "time": 0.0, "fanout": 0.0, "input_rows": 0.0, "cardinality_estimate": 0, "cardinality_fanout": 0, "operator_type": 0, "precode_bool": 0, "after_code_bool": 0, "group_by_read_bool": 0, "distinct_bool": 0, "TOP_bool": 0, "TOP_num": 0, "top_order_by_bool": 0, "skip_node_bool": 0, "skip_node_num": 0, "{": 1, "}": 1, "select?": 0, "start_optional": 0, "end_optional": 0, "IRI_ID\"...direct/P6\"": 0, "IRI_ID\"...direct/P279\"": 0, "IRI_ID\"...direct/P31\"": 0, "optional_section?": 0, "after_test_1op?": 0, "after_test_lvl": 0, "target_bracket": 1, "transitive_bracket": 0, "union_sort_lvl": 0, "sort_lvl": 0, "subquerie_lvl": 1, "union_sub_lvl": 1, "subquery_select?": 1}, "OP10": {"profile_text": "            time        30% fanout         0 input         1 rows\n            Warning: the cardinality estimate of the cost model differs greatly from the measured time. Cardinality estimate:       0.3 Fanout:         0\n              clear: (<V s_37_31_t5.O$101 an>)\n              clear on continue: (<V s_37_31_t5.O$101 an>)\n            s# 299 100 from DB.DBA.RDF_QUAD by RDF_QUAD        0.3 rows   \n            Key RDF_QUAD  ASC  (<V s_37_31_t5.O$101 an>)\n             inlined  P =  IRI_ID\"...direct/P6\"  ,  S =  IRI_ID\"...Q64\" \n            ", "profile_text_low_explain": "\n            time        25% fanout         0 input         1 rows\n            Warning: the cardinality estimate of the cost model differs greatly from the measured time. Cardinality estimate:       0.3 Fanout:         0\n            RDF_QUAD       0.3 rows(s_37_31_t5.O$101)\n             inlined  P =  IRI_ID\"...direct/P6\"  ,  S =  IRI_ID\"...Q64\" ", "time": 30.0, "fanout": 0.0, "input_rows": 1.0, "cardinality_estimate": 0.3, "cardinality_fanout": 0.0, "operator_type": 1, "precode_bool": 0, "after_code_bool": 0, "group_by_read_bool": 0, "distinct_bool": 0, "P": "IRI_ID\"...direct/P6\"", "P_math_op": "=", "S": "IRI_ID\"...Q64\"", "S_math_op": "=", "TOP_bool": 0, "TOP_num": 0, "top_order_by_bool": 0, "skip_node_bool": 0, "skip_node_num": 0, "{": 0, "}": 0, "select?": 0, "start_optional": 0, "end_optional": 0, "IRI_ID\"...direct/P6\"": 1, "IRI_ID\"...direct/P279\"": 0, "IRI_ID\"...direct/P31\"": 0, "optional_section?": 0, "after_test_1op?": 0, "after_test_lvl": 0, "target_bracket": 0, "transitive_bracket": 0, "union_sort_lvl": 0, "sort_lvl": 0, "subquerie_lvl": 1, "union_sub_lvl": 1, "subquery_select?": 0}, "OP11": {"profile_text": "            time         0% fanout         0 input         0 rows\n            Warning: the cardinality estimate of the cost model differs greatly from the measured time. Cardinality estimate:       0.3 Fanout:         0\n              clear: (<V s_37_19_t3.O$104 an>)\n              clear on continue: (<V s_37_19_t3.O$104 an>)\n            s# 309 103 from DB.DBA.RDF_QUAD by RDF_QUAD        0.3 rows   \n            Key RDF_QUAD  ASC  (<V s_37_19_t3.O$104 an>)\n             inlined  P =  IRI_ID\"...direct/P31\"  ,  S =  IRI_ID\"...Q64\" \n            row specs:  O LIKE <c T\u00f3>\n            \n            Precode:\n              0: <V __all_eq$106 x> := Call __all_eq (<V s_37_19_t3.O$104 an>)\n              5: BReturn 0\n              clear: (<V _::trans_obj_37_22$110 an>, <V _::trans_subj_37_21$109 rn>, <V __all_eq$106 x>)\n              clear on continue: (<V _::trans_subj_37_21$109 rn>, <V _::trans_obj_37_22$110 an>)$104 () \n            s# 319 108 Transitive dt dir 2, input: (<r __all_eq$27 via  Set309 Set299>)\n              input shadow: (<V __all_eq$323 x>)\n              output: (<V _::trans_subj_37_21$109 rn>)\n             Target:  (<V __all_eq$106 x>)\n              { ", "profile_text_low_explain": "\n            time         0% fanout         0 input         0 rows\n            Warning: the cardinality estimate of the cost model differs greatly from the measured time. Cardinality estimate:       0.3 Fanout:         0\n            RDF_QUAD       0.3 rows(s_37_19_t3.O$104)\n             inlined  P =  IRI_ID\"...direct/P31\"  ,  S =  IRI_ID\"...Q64\"  O LIKE <c T\u00f3>\n            Precode:\n              0: __all_eq$106 := Call __all_eq (s_37_19_t3.O$104)\n              5: BReturn 0\n            Transitive dt dir 2, input: (__all_eq$27)\n              input shadow: (__all_eq$323)\n              output: (_::trans_subj_37_21$109)\n             Target:  (__all_eq$106)\n              { ", "time": 0.0, "fanout": 0.0, "input_rows": 0.0, "cardinality_estimate": 0.3, "cardinality_fanout": 0.0, "operator_type": 1, "precode_bool": 1, "precode_text": "Precode:\n              0: <V __all_eq$106 x> := Call __all_eq (<V s_37_19_t3.O$104 an>)\n              5: BReturn 0", "after_code_bool": 0, "group_by_read_bool": 0, "distinct_bool": 0, "P": "IRI_ID\"...direct/P31\"", "P_math_op": "=", "S": "IRI_ID\"...Q64\"", "S_math_op": "=", "O_rs": "T\u00f3>", "O_rs_math_op": "LIKE", "TOP_bool": 0, "TOP_num": 0, "top_order_by_bool": 0, "skip_node_bool": 0, "skip_node_num": 0, "{": 1, "}": 0, "select?": 0, "start_optional": 0, "end_optional": 0, "IRI_ID\"...direct/P6\"": 0, "IRI_ID\"...direct/P279\"": 0, "IRI_ID\"...direct/P31\"": 1, "optional_section?": 0, "after_test_1op?": 0, "after_test_lvl": 0, "target_bracket": 1, "transitive_bracket": 1, "union_sort_lvl": 0, "sort_lvl": 0, "subquerie_lvl": 1, "union_sub_lvl": 1, "subquery_select?": 0}, "OP12": {"profile_text": "                time         0% fanout         0 input         0 rows\n                Warning: the cardinality estimate of the cost model differs greatly from the measured time. Cardinality estimate:       3.8 Fanout:         0\n                  clear: (<V t9.O$115 an>, <V t9.S$116 rn>, <V _::trans_obj_37_22$110 an>, <V _::trans_subj_37_21$109 rn>)\n                  clear on continue: (<V _::trans_subj_37_21$109 rn>, <V _::trans_obj_37_22$110 an>, <V t9.S$116 rn>, <V t9.O$115 an>)$323 (114 ) $329 (114 ) \n                s# 325 114 from DB.DBA.RDF_QUAD by RDF_QUAD_POGS        3.8 rows   \n                Key RDF_QUAD_POGS  ASC  (<V t9.S$116 rn>, <V t9.O$115 an>)\n                 P =  IRI_ID\"...direct/P279\"  ,  O = <v k___all_eq$329 Set331 an>\n                vector param casts: <V __all_eq$323 x>-> <v k___all_eq$329 Set331 an>\n                \n                After code:\n                  0: <V _::trans_subj_37_21$109 rn> :=  := artm <V t9.S$116 rn>\n                  4: <V _::trans_obj_37_22$110 an> :=  := artm <V t9.O$115 an>\n                  8: BReturn 0", "profile_text_low_explain": "\n                time         0% fanout         0 input         0 rows\n                Warning: the cardinality estimate of the cost model differs greatly from the measured time. Cardinality estimate:       3.8 Fanout:         0\n                RDF_QUAD_POGS       3.8 rows(t9.S$116, t9.O$115)\n                 P =  IRI_ID\"...direct/P279\"  ,  O = k___all_eq$329\n                \n                After code:\n                0: _::trans_subj_37_21$109 :=  := artm t9.S$116\n                4: _::trans_obj_37_22$110 :=  := artm t9.O$115\n                8: BReturn 0", "time": 0.0, "fanout": 0.0, "input_rows": 0.0, "cardinality_estimate": 3.8, "cardinality_fanout": 0.0, "operator_type": 1, "precode_bool": 0, "after_code_bool": 1, "after_code_text": "After code:\n                  0: <V _::trans_subj_37_21$109 rn> :=  := artm <V t9.S$116 rn>\n                  4: <V _::trans_obj_37_22$110 an> :=  := artm <V t9.O$115 an>\n                  8: BReturn 0", "group_by_read_bool": 0, "distinct_bool": 0, "P": "IRI_ID\"...direct/P279\"", "P_math_op": "=", "O": "k___all_eq", "O_math_op": "=", "TOP_bool": 0, "TOP_num": 0, "top_order_by_bool": 0, "skip_node_bool": 0, "skip_node_num": 0, "{": 0, "}": 0, "select?": 0, "start_optional": 0, "end_optional": 0, "IRI_ID\"...direct/P6\"": 0, "IRI_ID\"...direct/P279\"": 1, "IRI_ID\"...direct/P31\"": 0, "optional_section?": 0, "after_test_1op?": 0, "after_test_lvl": 0, "target_bracket": 1, "transitive_bracket": 1, "union_sort_lvl": 0, "sort_lvl": 0, "subquerie_lvl": 1, "union_sub_lvl": 1, "subquery_select?": 0}, "OP13": {"profile_text": "                time         0% fanout         0 input         0 rows\n                \n                s# 342 118 Subquery Select(<V _::trans_subj_37_21$109 rn>, <V _::trans_obj_37_22$110 an>)\n                  set no: <r step_set$111 via  Set325 Set331>\n              }\n            Reverse transitive node, input: (<V __all_eq$106 x>)\n              output: (<V _::trans_obj_37_22$110 an>)\n             Target:  (<V __all_eq$27 x>)\n              { ", "profile_text_low_explain": "\n                time         0% fanout         0 input         0 rows\n                Subquery Select(_::trans_subj_37_21$109, _::trans_obj_37_22$110)\n              }\n            Reverse transitive node, input: (__all_eq$106)\n              output: (_::trans_obj_37_22$110)\n             Target:  (__all_eq$27)\n              { ", "time": 0.0, "fanout": 0.0, "input_rows": 0.0, "cardinality_estimate": 0, "cardinality_fanout": 0, "operator_type": 0, "precode_bool": 0, "after_code_bool": 0, "group_by_read_bool": 0, "distinct_bool": 0, "TOP_bool": 0, "TOP_num": 0, "top_order_by_bool": 0, "skip_node_bool": 0, "skip_node_num": 0, "{": 1, "}": 1, "select?": 0, "start_optional": 0, "end_optional": 0, "IRI_ID\"...direct/P6\"": 0, "IRI_ID\"...direct/P279\"": 0, "IRI_ID\"...direct/P31\"": 0, "optional_section?": 0, "after_test_1op?": 0, "after_test_lvl": 0, "target_bracket": 2, "transitive_bracket": 1, "union_sort_lvl": 0, "sort_lvl": 0, "subquerie_lvl": 1, "union_sub_lvl": 1, "subquery_select?": 1}, "OP14": {"profile_text": "                time         0% fanout         0 input         0 rows\n                Warning: the cardinality estimate of the cost model differs greatly from the measured time. Cardinality estimate:       1.4 Fanout:         0\n                  clear: (<V t9.O$140 an>, <V t9.S$141 rn>, <V _::trans_obj_37_22$110 an>, <V _::trans_subj_37_21$109 rn>)\n                  clear on continue: (<V _::trans_subj_37_21$109 rn>, <V _::trans_obj_37_22$110 an>, <V t9.S$141 rn>, <V t9.O$140 an>)$353 (139 ) $359 (139 ) \n                s# 355 139 from DB.DBA.RDF_QUAD by RDF_QUAD        1.4 rows   \n                Key RDF_QUAD  ASC  (<V t9.S$141 rn>, <V t9.O$140 an>)\n                 inlined  P =  IRI_ID\"...direct/P279\"  ,  S = <v k___all_eq$359 Set361 rn>\n                vector param casts: <V __all_eq$353 x>-> <v k___all_eq$359 Set361 rn>\n                \n                After code:\n                  0: <V _::trans_subj_37_21$109 rn> :=  := artm <V t9.S$141 rn>\n                  4: <V _::trans_obj_37_22$110 an> :=  := artm <V t9.O$140 an>\n                  8: BReturn 0", "profile_text_low_explain": "\n                time         0% fanout         0 input         0 rows\n                Warning: the cardinality estimate of the cost model differs greatly from the measured time. Cardinality estimate:       1.4 Fanout:         0\n                RDF_QUAD       1.4 rows(t9.S$141, t9.O$140)\n                 inlined  P =  IRI_ID\"...direct/P279\"  ,  S = k___all_eq$359\n                \n                After code:\n                0: _::trans_subj_37_21$109 :=  := artm t9.S$141\n                4: _::trans_obj_37_22$110 :=  := artm t9.O$140\n                8: BReturn 0", "time": 0.0, "fanout": 0.0, "input_rows": 0.0, "cardinality_estimate": 1.4, "cardinality_fanout": 0.0, "operator_type": 1, "precode_bool": 0, "after_code_bool": 1, "after_code_text": "After code:\n                  0: <V _::trans_subj_37_21$109 rn> :=  := artm <V t9.S$141 rn>\n                  4: <V _::trans_obj_37_22$110 an> :=  := artm <V t9.O$140 an>\n                  8: BReturn 0", "group_by_read_bool": 0, "distinct_bool": 0, "P": "IRI_ID\"...direct/P279\"", "P_math_op": "=", "S": "k___all_eq", "S_math_op": "=", "TOP_bool": 0, "TOP_num": 0, "top_order_by_bool": 0, "skip_node_bool": 0, "skip_node_num": 0, "{": 0, "}": 0, "select?": 0, "start_optional": 0, "end_optional": 0, "IRI_ID\"...direct/P6\"": 0, "IRI_ID\"...direct/P279\"": 1, "IRI_ID\"...direct/P31\"": 0, "optional_section?": 0, "after_test_1op?": 0, "after_test_lvl": 0, "target_bracket": 2, "transitive_bracket": 0, "union_sort_lvl": 0, "sort_lvl": 0, "subquerie_lvl": 1, "union_sub_lvl": 1, "subquery_select?": 0}, "OP15": {"profile_text": "                time         0% fanout         0 input         0 rows\n                $109 () \n                s# 370 143 Subquery Select(<V _::trans_subj_37_21$109 rn>, <V _::trans_obj_37_22$110 an>)\n                  set no: <r step_set$136 via  Set355 Set361>\n              }", "profile_text_low_explain": "\n                time         0% fanout         0 input         0 rows\n                Subquery Select(_::trans_subj_37_21$109, _::trans_obj_37_22$110)\n              }", "time": 0.0, "fanout": 0.0, "input_rows": 0.0, "cardinality_estimate": 0, "cardinality_fanout": 0, "operator_type": 0, "precode_bool": 0, "after_code_bool": 0, "group_by_read_bool": 0, "distinct_bool": 0, "TOP_bool": 0, "TOP_num": 0, "top_order_by_bool": 0, "skip_node_bool": 0, "skip_node_num": 0, "{": 0, "}": 1, "select?": 0, "start_optional": 0, "end_optional": 0, "IRI_ID\"...direct/P6\"": 0, "IRI_ID\"...direct/P279\"": 0, "IRI_ID\"...direct/P31\"": 0, "optional_section?": 0, "after_test_1op?": 0, "after_test_lvl": 0, "target_bracket": 2, "transitive_bracket": 0, "union_sort_lvl": 0, "sort_lvl": 0, "subquerie_lvl": 1, "union_sub_lvl": 1, "subquery_select?": 1}, "OP16": {"profile_text": "            time         0% fanout         0 input         0 rows\n              clear: (<V var1$30 a>)$101 (108 103 ) $110 () \n            s# 387 382 END Node\n            After test:\n              0: if (<V _::trans_obj_37_22$110 an> =  IRI_ID\"...Q515\" ) then 4 else 5 unkn 5\n              4: BReturn 1\n              5: BReturn 0\n            After code:\n              0: <V var1$30 a> :=  := artm <r s_37_31_t5.O$101 via  Set387 Set319 Set309>\n              4: BReturn 0", "profile_text_low_explain": "\n            time         0% fanout         0 input         0 rows\n            END Node\n            After test:\n            0: if (_::trans_obj_37_22$110 =  IRI_ID\"...Q515\" ) then 4 else 5 unkn 5\n            4: BReturn 1\n            5: BReturn 0\n            \n            After code:\n            0: var1$30 :=  := artm s_37_31_t5.O$101\n            4: BReturn 0", "time": 0.0, "fanout": 0.0, "input_rows": 0.0, "cardinality_estimate": 0, "cardinality_fanout": 0, "operator_type": 0, "precode_bool": 0, "after_code_bool": 1, "after_code_text": "After code:\n              0: <V var1$30 a> :=  := artm <r s_37_31_t5.O$101 via  Set387 Set319 Set309>\n              4: BReturn 0", "group_by_read_bool": 0, "distinct_bool": 0, "TOP_bool": 0, "TOP_num": 0, "top_order_by_bool": 0, "skip_node_bool": 0, "skip_node_num": 0, "{": 0, "}": 0, "select?": 0, "start_optional": 0, "end_optional": 0, "IRI_ID\"...direct/P6\"": 0, "IRI_ID\"...direct/P279\"": 0, "IRI_ID\"...direct/P31\"": 0, "optional_section?": 0, "after_test_lvl": 1, "after_test_1op?": 1, "target_bracket": 1, "transitive_bracket": 0, "union_sort_lvl": 0, "sort_lvl": 0, "subquerie_lvl": 1, "union_sub_lvl": 1, "subquery_select?": 0}, "OP17": {"profile_text": "            time         0% fanout         0 input         0 rows\n            \n            Subquery Select(<V var1$30 a>)\n              set no: <r set_no$31 via  Set387 Set319 Set309 Set299>\n          }\n      }\n    \n    After code:\n      0: <V var1$168 a> := Call __ro2sq (<V var1$30 a>)\n      5: BReturn 0", "profile_text_low_explain": "\n            time         0% fanout         0 input         0 rows\n            Subquery Select(var1$30)\n          }\n      }\n    \n    After code:\n    0: var1$168 := Call __ro2sq (var1$30)\n    5: BReturn 0", "time": 0.0, "fanout": 0.0, "input_rows": 0.0, "cardinality_estimate": 0, "cardinality_fanout": 0, "operator_type": 0, "precode_bool": 0, "after_code_bool": 1, "after_code_text": "After code:\n      0: <V var1$168 a> := Call __ro2sq (<V var1$30 a>)\n      5: BReturn 0", "group_by_read_bool": 0, "distinct_bool": 0, "TOP_bool": 0, "TOP_num": 0, "top_order_by_bool": 0, "skip_node_bool": 0, "skip_node_num": 0, "{": 0, "}": 2, "select?": 0, "start_optional": 0, "end_optional": 0, "IRI_ID\"...direct/P6\"": 0, "IRI_ID\"...direct/P279\"": 0, "IRI_ID\"...direct/P31\"": 0, "optional_section?": 0, "after_test_1op?": 0, "after_test_lvl": 0, "target_bracket": 1, "transitive_bracket": 0, "union_sort_lvl": 0, "sort_lvl": 0, "subquerie_lvl": 1, "union_sub_lvl": 1, "subquery_select?": 1}, "OP18": {"profile_text": "    time         0% fanout         0 input         0 rows\n    $168 (29 ) $176 (29 177 ) \n    s# 402 170 Select (<V var1$168 a>)\n      set no: <r set_ctr$176 via  Set188>\n  ", "profile_text_low_explain": "\n    time         0% fanout         0 input         0 rows\n    Select (var1$168)\n  ", "time": 0.0, "fanout": 0.0, "input_rows": 0.0, "cardinality_estimate": 0, "cardinality_fanout": 0, "operator_type": 0, "precode_bool": 0, "after_code_bool": 0, "group_by_read_bool": 0, "distinct_bool": 0, "TOP_bool": 0, "TOP_num": 0, "top_order_by_bool": 0, "skip_node_bool": 0, "skip_node_num": 0, "{": 0, "}": 0, "select?": 1, "start_optional": 0, "end_optional": 0, "IRI_ID\"...direct/P6\"": 0, "IRI_ID\"...direct/P279\"": 0, "IRI_ID\"...direct/P31\"": 0, "optional_section?": 0, "after_test_1op?": 0, "after_test_lvl": 0, "target_bracket": 1, "transitive_bracket": 0, "union_sort_lvl": 0, "sort_lvl": 0, "subquerie_lvl": 1, "union_sub_lvl": 1, "subquery_select?": 0}, "GENERAL_FEATURES": {"LIMIT": 0, "precompiled": {"ql_rt_msec": "0", "ql_rt_clocks": "1%", "ql_rnd_rows": "2", "ql_seq_rows": "0", "ql_same_seg": "0%", "ql_same_page": "0%", "ql_disk_reads": "0", "ql_spec_disk_reads": "0", "ql_cl_wait_clocks": "0"}, "compiled": {"ql_c_msec": "5", "ql_c_disk": "0", "ql_c_clocks": "0%", "ql_cl_messages": "0", "ql_c_cl_wait": "0%"}}}