{"OP1": {"profile_text": "    time    0.0008% fanout         1 input         1 rows\n      clear: (<V set_ctr$62 in>)\n    s# 65 63 cluster outer seq start, set no <V set_ctr$62 in>    \n    save ctx:()", "profile_text_low_explain": "\n    time   0.00081% fanout         1 input         1 rows", "time": 0.0008, "fanout": 1.0, "input_rows": 1.0, "cardinality_estimate": 0, "cardinality_fanout": 0, "operator_type": 0, "precode_bool": 0, "after_code_bool": 0, "group_by_read_bool": 0, "distinct_bool": 0, "TOP_bool": 0, "TOP_num": 0, "top_order_by_bool": 0, "skip_node_bool": 0, "skip_node_num": 0, "{": 0, "}": 0, "select?": 0, "start_optional": 0, "end_optional": 0, "IRI_ID\"...direct/P570\"": 0, "optional_section?": 0, "after_test_1op?": 0, "after_test_lvl": 0, "target_bracket": 0, "transitive_bracket": 0, "union_sort_lvl": 0, "sort_lvl": 0, "subquerie_lvl": 0, "union_sub_lvl": 0, "subquery_select?": 0}, "OP2": {"profile_text": "    time     0.026% fanout         1 input         1 rows\n    Precode:\n      0: <V DB.DBA.RDF_MAKE_LONG_OF_TYPEDSQLVAL_STRINGS$27 a> := Call DB.DBA.RDF_MAKE_LONG_OF_TYPEDSQLVAL_STRINGS (<c 987-04-31T23:59:59Z>, <tag 217 c http://www.w3.org/2001/XMLSchema#dateTime>, <DB_NULL>)\n      7: BReturn 0\n      clear: (<V set_no$31 i>, <V DB.DBA.RDF_MAKE_LONG_OF_TYPEDSQLVAL_STRINGS$27 a>)\n    s# 74 53 cluster outer seq start, set no <V set_no$31 i>    \n    save ctx:()", "profile_text_low_explain": "\n    time     0.026% fanout         1 input         1 rows\n    Precode:\n      0: DB.DBA.RDF_MAKE_LONG_OF_TYPEDSQLVAL_STRINGS$27 := Call DB.DBA.RDF_MAKE_LONG_OF_TYPEDSQLVAL_STRINGS (<c 987-04-31T23:59:59Z>, <tag 217 c http://www.w3.org/2001/XMLSchema#dateTime>, <DB_NULL>)\n      7: BReturn 0", "time": 0.026, "fanout": 1.0, "input_rows": 1.0, "cardinality_estimate": 0, "cardinality_fanout": 0, "operator_type": 0, "precode_bool": 1, "precode_text": "Precode:\n      0: <V DB.DBA.RDF_MAKE_LONG_OF_TYPEDSQLVAL_STRINGS$27 a> := Call DB.DBA.RDF_MAKE_LONG_OF_TYPEDSQLVAL_STRINGS (<c 987-04-31T23:59:59Z>, <tag 217 c http://www.w3.org/2001/XMLSchema#dateTime>, <DB_NULL>)\n      7: BReturn 0", "after_code_bool": 0, "group_by_read_bool": 0, "distinct_bool": 0, "TOP_bool": 0, "TOP_num": 0, "top_order_by_bool": 0, "skip_node_bool": 0, "skip_node_num": 0, "{": 0, "}": 0, "select?": 0, "start_optional": 0, "end_optional": 0, "IRI_ID\"...direct/P570\"": 0, "optional_section?": 0, "after_test_1op?": 0, "after_test_lvl": 0, "target_bracket": 0, "transitive_bracket": 0, "union_sort_lvl": 0, "sort_lvl": 0, "subquerie_lvl": 0, "union_sub_lvl": 0, "subquery_select?": 0}, "OP3": {"profile_text": "    time       5.2% fanout    209273 input         1 rows\n      clear: (<V s_37_2_t0.S$33 rn>, <V s_37_2_t0.O$34 an>)\n      clear on continue: (<V s_37_2_t0.S$33 rn>, <V s_37_2_t0.O$34 an>)\n    s# 83 32 from DB.DBA.RDF_QUAD by RDF_QUAD_POGS    1.4e+05 rows   \n    Key RDF_QUAD_POGS  ASC  (<V s_37_2_t0.O$34 an>, <V s_37_2_t0.S$33 rn>)\n     P =  IRI_ID\"...direct/P570\"  ,  O >= <tag 211 c 0987-04-01 00:00:00Z>\n    row specs:  O >= <tag 211 c 0987-04-01 00:00:00Z>\n    ", "profile_text_low_explain": "\n    time       5.1% fanout    209273 input         1 rows\n    RDF_QUAD_POGS   1.4e+05 rows(s_37_2_t0.O$34, s_37_2_t0.S$33)\n     P =  IRI_ID\"...direct/P570\"  ,  O >= <tag 211 c 0987-04-01 00:00:00Z> O >= <tag 211 c 0987-04-01 00:00:00Z>", "time": 5.2, "fanout": 209273.0, "input_rows": 1.0, "cardinality_estimate": 0, "cardinality_fanout": 0, "operator_type": 1, "precode_bool": 0, "after_code_bool": 0, "group_by_read_bool": 0, "distinct_bool": 0, "P": "IRI_ID\"...direct/P570\"", "P_math_op": "=", "O": "<tag", "O_math_op": ">=", "O_rs": "<tag", "O_rs_math_op": ">=", "TOP_bool": 0, "TOP_num": 0, "top_order_by_bool": 0, "skip_node_bool": 0, "skip_node_num": 0, "{": 0, "}": 0, "select?": 0, "start_optional": 0, "end_optional": 0, "IRI_ID\"...direct/P570\"": 1, "optional_section?": 0, "after_test_1op?": 0, "after_test_lvl": 0, "target_bracket": 0, "transitive_bracket": 0, "union_sort_lvl": 0, "sort_lvl": 0, "subquerie_lvl": 0, "union_sub_lvl": 0, "subquery_select?": 0}, "OP4": {"profile_text": "    time        95% fanout         0 input    209273 rows\n      clear: (<V DB.DBA.RDF_LONG_CMP$38 i>, <V __ro2lo$36 a>)$34 () $27 (32 53 ) \n    s# 99 94 END Node\n    After test:\n      0: <V __ro2lo$36 a> := Call __ro2lo (<V s_37_2_t0.O$34 an>)\n      5: <V DB.DBA.RDF_LONG_CMP$38 i> := Call DB.DBA.RDF_LONG_CMP (<V __ro2lo$36 a>, <r DB.DBA.RDF_MAKE_LONG_OF_TYPEDSQLVAL_STRINGS$27 via  Set83 Set74>)\n      12: if (<V DB.DBA.RDF_LONG_CMP$38 i> <=  0 ) then 16 else 17 unkn 17\n      16: BReturn 1\n      17: BReturn 0", "profile_text_low_explain": "\n    time        95% fanout         0 input    209273 rows\n    END Node\n    After test:\n    0: __ro2lo$36 := Call __ro2lo (s_37_2_t0.O$34)\n    5: DB.DBA.RDF_LONG_CMP$38 := Call DB.DBA.RDF_LONG_CMP (__ro2lo$36, DB.DBA.RDF_MAKE_LONG_OF_TYPEDSQLVAL_STRINGS$27)\n    12: if (DB.DBA.RDF_LONG_CMP$38 <=  0 ) then 16 else 17 unkn 17\n    16: BReturn 1\n    17: BReturn 0", "time": 95.0, "fanout": 0.0, "input_rows": 209273.0, "cardinality_estimate": 0, "cardinality_fanout": 0, "operator_type": 0, "precode_bool": 0, "after_code_bool": 0, "group_by_read_bool": 0, "distinct_bool": 0, "TOP_bool": 0, "TOP_num": 0, "top_order_by_bool": 0, "skip_node_bool": 0, "skip_node_num": 0, "{": 0, "}": 0, "select?": 0, "start_optional": 0, "end_optional": 0, "IRI_ID\"...direct/P570\"": 0, "optional_section?": 0, "after_test_lvl": 1, "after_test_1op?": 1, "target_bracket": 0, "transitive_bracket": 0, "union_sort_lvl": 0, "sort_lvl": 0, "subquerie_lvl": 0, "union_sub_lvl": 0, "subquery_select?": 0}, "OP5": {"profile_text": "    time         0% fanout         0 input         0 rows\n      clear: (<V var1$30 rn>)$33 (94 ) \n    s# 107 40 Distinct (HASH) set no <r set_no$31 via  Set99 Set83>(<r s_37_2_t0.S$33 via  Set99>)\n    After code:\n      0: <V var1$30 rn> :=  := artm <r s_37_2_t0.S$33 via  Set107 Set99>\n      4: BReturn 0", "profile_text_low_explain": "\n    time         0% fanout         0 input         0 rows\n    Distinct (s_37_2_t0.S$33)\n    \n    After code:\n    0: var1$30 :=  := artm s_37_2_t0.S$33\n    4: BReturn 0", "time": 0.0, "fanout": 0.0, "input_rows": 0.0, "cardinality_estimate": 0, "cardinality_fanout": 0, "operator_type": 0, "precode_bool": 0, "after_code_bool": 1, "after_code_text": "After code:\n      0: <V var1$30 rn> :=  := artm <r s_37_2_t0.S$33 via  Set107 Set99>\n      4: BReturn 0", "group_by_read_bool": 0, "distinct_bool": 1, "TOP_bool": 0, "TOP_num": 0, "top_order_by_bool": 0, "skip_node_bool": 0, "skip_node_num": 0, "{": 0, "}": 0, "select?": 0, "start_optional": 0, "end_optional": 0, "IRI_ID\"...direct/P570\"": 0, "optional_section?": 0, "after_test_1op?": 0, "after_test_lvl": 0, "target_bracket": 0, "transitive_bracket": 0, "union_sort_lvl": 0, "sort_lvl": 0, "subquerie_lvl": 0, "union_sub_lvl": 0, "subquery_select?": 0}, "OP6": {"profile_text": "    time         0% fanout         0 input         0 rows\n      clear: (<V var1$54 a>)$31 (40 94 32 53 ) $30 (40 ) \n    s# 116 46 Subquery Select(<V var1$30 rn>)\n      set no: <r set_no$31 via  Set107 Set99 Set83>\n    After code:\n      0: <V var1$54 a> := Call __ro2sq (<V var1$30 rn>)\n      5: BReturn 0", "profile_text_low_explain": "\n    time         0% fanout         0 input         0 rows\n    Subquery Select(var1$30)\n    \n    After code:\n    0: var1$54 := Call __ro2sq (var1$30)\n    5: BReturn 0", "time": 0.0, "fanout": 0.0, "input_rows": 0.0, "cardinality_estimate": 0, "cardinality_fanout": 0, "operator_type": 0, "precode_bool": 0, "after_code_bool": 1, "after_code_text": "After code:\n      0: <V var1$54 a> := Call __ro2sq (<V var1$30 rn>)\n      5: BReturn 0", "group_by_read_bool": 0, "distinct_bool": 0, "TOP_bool": 0, "TOP_num": 0, "top_order_by_bool": 0, "skip_node_bool": 0, "skip_node_num": 0, "{": 0, "}": 0, "select?": 0, "start_optional": 0, "end_optional": 0, "IRI_ID\"...direct/P570\"": 0, "optional_section?": 0, "after_test_1op?": 0, "after_test_lvl": 0, "target_bracket": 0, "transitive_bracket": 0, "union_sort_lvl": 0, "sort_lvl": 0, "subquerie_lvl": 0, "union_sub_lvl": 0, "subquery_select?": 1}, "OP7": {"profile_text": "    time         0% fanout         0 input         0 rows\n    $62 (46 40 94 32 53 63 ) $54 (46 ) \n    s# 123 56 Select (<V var1$54 a>)\n      set no: <r set_ctr$62 via  Set116>\n  ", "profile_text_low_explain": "\n    time         0% fanout         0 input         0 rows\n    Select (var1$54)\n  ", "time": 0.0, "fanout": 0.0, "input_rows": 0.0, "cardinality_estimate": 0, "cardinality_fanout": 0, "operator_type": 0, "precode_bool": 0, "after_code_bool": 0, "group_by_read_bool": 0, "distinct_bool": 0, "TOP_bool": 0, "TOP_num": 0, "top_order_by_bool": 0, "skip_node_bool": 0, "skip_node_num": 0, "{": 0, "}": 0, "select?": 1, "start_optional": 0, "end_optional": 0, "IRI_ID\"...direct/P570\"": 0, "optional_section?": 0, "after_test_1op?": 0, "after_test_lvl": 0, "target_bracket": 0, "transitive_bracket": 0, "union_sort_lvl": 0, "sort_lvl": 0, "subquerie_lvl": 0, "union_sub_lvl": 0, "subquery_select?": 0}, "GENERAL_FEATURES": {"LIMIT": 0, "precompiled": {"ql_rt_msec": "306", "ql_rt_clocks": "86%", "ql_rnd_rows": "1", "ql_seq_rows": "211748", "ql_same_seg": "0%", "ql_same_page": "0%", "ql_disk_reads": "0", "ql_spec_disk_reads": "0", "ql_cl_wait_clocks": "0"}, "compiled": {"ql_c_msec": "46", "ql_c_disk": "1", "ql_c_clocks": "9.35058%", "ql_cl_messages": "0", "ql_c_cl_wait": "0%"}}}