{"OP1": {"profile_text": "    time       7.5% fanout         1 input         1 rows\n      clear: (<V set_ctr$64 in>)\n    s# 67 65 cluster outer seq start, set no <V set_ctr$64 in>    \n    save ctx:()", "profile_text_low_explain": "\n    time       5.2% fanout         1 input         1 rows", "time": 7.5, "fanout": 1.0, "input_rows": 1.0, "cardinality_estimate": 0, "cardinality_fanout": 0, "operator_type": 0, "precode_bool": 0, "after_code_bool": 0, "group_by_read_bool": 0, "distinct_bool": 0, "TOP_bool": 0, "TOP_num": 0, "top_order_by_bool": 0, "skip_node_bool": 0, "skip_node_num": 0, "{": 0, "}": 0, "select?": 0, "start_optional": 0, "end_optional": 0, "IRI_ID\"...direct/P31\"": 0, "IRI_ID\"...direct/P625\"": 0, "optional_section?": 0, "after_test_1op?": 0, "after_test_lvl": 0, "target_bracket": 0, "transitive_bracket": 0, "union_sort_lvl": 0, "sort_lvl": 0, "subquerie_lvl": 0, "union_sub_lvl": 0, "subquery_select?": 0}, "OP2": {"profile_text": "    time       1.8% fanout         1 input         1 rows\n      clear: (<V set_no$30 i>)\n    s# 76 53 cluster outer seq start, set no <V set_no$30 i>    \n    save ctx:()", "profile_text_low_explain": "\n    time       1.3% fanout         1 input         1 rows", "time": 1.8, "fanout": 1.0, "input_rows": 1.0, "cardinality_estimate": 0, "cardinality_fanout": 0, "operator_type": 0, "precode_bool": 0, "after_code_bool": 0, "group_by_read_bool": 0, "distinct_bool": 0, "TOP_bool": 0, "TOP_num": 0, "top_order_by_bool": 0, "skip_node_bool": 0, "skip_node_num": 0, "{": 0, "}": 0, "select?": 0, "start_optional": 0, "end_optional": 0, "IRI_ID\"...direct/P31\"": 0, "IRI_ID\"...direct/P625\"": 0, "optional_section?": 0, "after_test_1op?": 0, "after_test_lvl": 0, "target_bracket": 0, "transitive_bracket": 0, "union_sort_lvl": 0, "sort_lvl": 0, "subquerie_lvl": 0, "union_sub_lvl": 0, "subquery_select?": 0}, "OP3": {"profile_text": "    time        91% fanout         0 input         1 rows\n    Warning: the cardinality estimate of the cost model differs greatly from the measured time. Cardinality estimate:       0.3 Fanout:         0\n      clear: (<V s_37_6_t1.S$32 rn>)\n      clear on continue: (<V s_37_6_t1.S$32 rn>)\n    s# 85 31 from DB.DBA.RDF_QUAD by RDF_QUAD_POGS        0.3 rows   \n    Key RDF_QUAD_POGS  ASC  (<V s_37_6_t1.S$32 rn>)\n     P =  IRI_ID\"...direct/P31\"  ,  O =  IRI_ID\"...Q31\" \n    ", "profile_text_low_explain": "\n    time        93% fanout         0 input         1 rows\n    Warning: the cardinality estimate of the cost model differs greatly from the measured time. Cardinality estimate:       0.3 Fanout:         0\n    RDF_QUAD_POGS       0.3 rows(s_37_6_t1.S$32)\n     P =  IRI_ID\"...direct/P31\"  ,  O =  IRI_ID\"...Q31\" ", "time": 91.0, "fanout": 0.0, "input_rows": 1.0, "cardinality_estimate": 0.3, "cardinality_fanout": 0.0, "operator_type": 1, "precode_bool": 0, "after_code_bool": 0, "group_by_read_bool": 0, "distinct_bool": 0, "P": "IRI_ID\"...direct/P31\"", "P_math_op": "=", "O": "IRI_ID\"...Q31\"", "O_math_op": "=", "TOP_bool": 0, "TOP_num": 0, "top_order_by_bool": 0, "skip_node_bool": 0, "skip_node_num": 0, "{": 0, "}": 0, "select?": 0, "start_optional": 0, "end_optional": 0, "IRI_ID\"...direct/P31\"": 1, "IRI_ID\"...direct/P625\"": 0, "optional_section?": 0, "after_test_1op?": 0, "after_test_lvl": 0, "target_bracket": 0, "transitive_bracket": 0, "union_sort_lvl": 0, "sort_lvl": 0, "subquerie_lvl": 0, "union_sub_lvl": 0, "subquery_select?": 0}, "OP4": {"profile_text": "    time         0% fanout         0 input         0 rows\n    Warning: the cardinality estimate of the cost model differs greatly from the measured time. Cardinality estimate:   0.00054 Fanout:         0\n      clear: (<V s_37_6_t0.S$35 rn>)\n      clear on continue: (<V s_37_6_t0.S$35 rn>)$32 () \n    s# 95 34 from DB.DBA.RDF_QUAD by RDF_QUAD_POGS    0.00054 rows   \n    Key RDF_QUAD_POGS  ASC  (<V s_37_6_t0.S$35 rn>)\n     inlined  P =  IRI_ID\"...direct/P31\"  ,  O =  IRI_ID\"...Q1248784\"  ,  S = <V s_37_6_t1.S$32 rn>\n    ", "profile_text_low_explain": "\n    time         0% fanout         0 input         0 rows\n    Warning: the cardinality estimate of the cost model differs greatly from the measured time. Cardinality estimate:   0.00054 Fanout:         0\n    RDF_QUAD_POGS   0.00054 rows(s_37_6_t0.S$35)\n     inlined  P =  IRI_ID\"...direct/P31\"  ,  O =  IRI_ID\"...Q1248784\"  ,  S = s_37_6_t1.S$32", "time": 0.0, "fanout": 0.0, "input_rows": 0.0, "cardinality_estimate": 0.00054, "cardinality_fanout": 0.0, "operator_type": 1, "precode_bool": 0, "after_code_bool": 0, "group_by_read_bool": 0, "distinct_bool": 0, "P": "IRI_ID\"...direct/P31\"", "P_math_op": "=", "O": "IRI_ID\"...Q1248784\"", "O_math_op": "=", "S": "s_37_6_t1.S", "S_math_op": "=", "TOP_bool": 0, "TOP_num": 0, "top_order_by_bool": 0, "skip_node_bool": 0, "skip_node_num": 0, "{": 0, "}": 0, "select?": 0, "start_optional": 0, "end_optional": 0, "IRI_ID\"...direct/P31\"": 1, "IRI_ID\"...direct/P625\"": 0, "optional_section?": 0, "after_test_1op?": 0, "after_test_lvl": 0, "target_bracket": 0, "transitive_bracket": 0, "union_sort_lvl": 0, "sort_lvl": 0, "subquerie_lvl": 0, "union_sub_lvl": 0, "subquery_select?": 0}, "OP5": {"profile_text": "    time         0% fanout         0 input         0 rows\n    Warning: the cardinality estimate of the cost model differs greatly from the measured time. Cardinality estimate:       1.1 Fanout:         0\n      clear: (<V s_37_6_t2.O$38 an>)\n      clear on continue: (<V s_37_6_t2.O$38 an>)\n    s# 105 37 from DB.DBA.RDF_QUAD by RDF_QUAD        1.1 rows   \n    Key RDF_QUAD  ASC  (<V s_37_6_t2.O$38 an>)\n     inlined  P =  IRI_ID\"...direct/P625\"  ,  S = <V s_37_6_t0.S$35 rn>\n    ", "profile_text_low_explain": "\n    time         0% fanout         0 input         0 rows\n    Warning: the cardinality estimate of the cost model differs greatly from the measured time. Cardinality estimate:       1.1 Fanout:         0\n    RDF_QUAD       1.1 rows(s_37_6_t2.O$38)\n     inlined  P =  IRI_ID\"...direct/P625\"  ,  S = s_37_6_t0.S$35", "time": 0.0, "fanout": 0.0, "input_rows": 0.0, "cardinality_estimate": 1.1, "cardinality_fanout": 0.0, "operator_type": 1, "precode_bool": 0, "after_code_bool": 0, "group_by_read_bool": 0, "distinct_bool": 0, "P": "IRI_ID\"...direct/P625\"", "P_math_op": "=", "S": "s_37_6_t0.S", "S_math_op": "=", "TOP_bool": 0, "TOP_num": 0, "top_order_by_bool": 0, "skip_node_bool": 0, "skip_node_num": 0, "{": 0, "}": 0, "select?": 0, "start_optional": 0, "end_optional": 0, "IRI_ID\"...direct/P31\"": 0, "IRI_ID\"...direct/P625\"": 1, "optional_section?": 0, "after_test_1op?": 0, "after_test_lvl": 0, "target_bracket": 0, "transitive_bracket": 0, "union_sort_lvl": 0, "sort_lvl": 0, "subquerie_lvl": 0, "union_sub_lvl": 0, "subquery_select?": 0}, "OP6": {"profile_text": "    time         0% fanout         0 input         0 rows\n      clear: (<V var2$29 an>, <V var1$28 rn>)$35 (37 ) $38 () \n    s# 115 40 Distinct (HASH) set no <r set_no$30 via  Set105 Set95 Set85>(<r s_37_6_t0.S$35 via  Set105>, <V s_37_6_t2.O$38 an>)\n    After code:\n      0: <V var1$28 rn> :=  := artm <r s_37_6_t0.S$35 via  Set115 Set105>\n      4: <V var2$29 an> :=  := artm <r s_37_6_t2.O$38 via  Set115>\n      8: BReturn 0", "profile_text_low_explain": "\n    time         0% fanout         0 input         0 rows\n    Distinct (s_37_6_t0.S$35, s_37_6_t2.O$38)\n    \n    After code:\n    0: var1$28 :=  := artm s_37_6_t0.S$35\n    4: var2$29 :=  := artm s_37_6_t2.O$38\n    8: BReturn 0", "time": 0.0, "fanout": 0.0, "input_rows": 0.0, "cardinality_estimate": 0, "cardinality_fanout": 0, "operator_type": 0, "precode_bool": 0, "after_code_bool": 1, "after_code_text": "After code:\n      0: <V var1$28 rn> :=  := artm <r s_37_6_t0.S$35 via  Set115 Set105>\n      4: <V var2$29 an> :=  := artm <r s_37_6_t2.O$38 via  Set115>\n      8: BReturn 0", "group_by_read_bool": 0, "distinct_bool": 1, "TOP_bool": 0, "TOP_num": 0, "top_order_by_bool": 0, "skip_node_bool": 0, "skip_node_num": 0, "{": 0, "}": 0, "select?": 0, "start_optional": 0, "end_optional": 0, "IRI_ID\"...direct/P31\"": 0, "IRI_ID\"...direct/P625\"": 0, "optional_section?": 0, "after_test_1op?": 0, "after_test_lvl": 0, "target_bracket": 0, "transitive_bracket": 0, "union_sort_lvl": 0, "sort_lvl": 0, "subquerie_lvl": 0, "union_sub_lvl": 0, "subquery_select?": 0}, "OP7": {"profile_text": "    time         0% fanout         0 input         0 rows\n      clear: (<V var2$56 a>, <V var1$54 a>)$28 (40 ) $29 (40 ) $30 (40 37 34 31 53 ) \n    s# 125 46 Subquery Select(<V var1$28 rn>, <V var2$29 an>)\n      set no: <r set_no$30 via  Set115 Set105 Set95 Set85>\n    After code:\n      0: <V var1$54 a> := Call __ro2sq (<V var1$28 rn>)\n      5: <V var2$56 a> := Call __ro2sq (<V var2$29 an>)\n      10: BReturn 0", "profile_text_low_explain": "\n    time         0% fanout         0 input         0 rows\n    Subquery Select(var1$28, var2$29)\n    \n    After code:\n    0: var1$54 := Call __ro2sq (var1$28)\n    5: var2$56 := Call __ro2sq (var2$29)\n    10: BReturn 0", "time": 0.0, "fanout": 0.0, "input_rows": 0.0, "cardinality_estimate": 0, "cardinality_fanout": 0, "operator_type": 0, "precode_bool": 0, "after_code_bool": 1, "after_code_text": "After code:\n      0: <V var1$54 a> := Call __ro2sq (<V var1$28 rn>)\n      5: <V var2$56 a> := Call __ro2sq (<V var2$29 an>)\n      10: BReturn 0", "group_by_read_bool": 0, "distinct_bool": 0, "TOP_bool": 0, "TOP_num": 0, "top_order_by_bool": 0, "skip_node_bool": 0, "skip_node_num": 0, "{": 0, "}": 0, "select?": 0, "start_optional": 0, "end_optional": 0, "IRI_ID\"...direct/P31\"": 0, "IRI_ID\"...direct/P625\"": 0, "optional_section?": 0, "after_test_1op?": 0, "after_test_lvl": 0, "target_bracket": 0, "transitive_bracket": 0, "union_sort_lvl": 0, "sort_lvl": 0, "subquerie_lvl": 0, "union_sub_lvl": 0, "subquery_select?": 1}, "OP8": {"profile_text": "    time         0% fanout         0 input         0 rows\n    $64 (46 40 37 34 31 53 65 ) $54 (46 ) $56 (46 ) \n    s# 132 58 Select (<V var1$54 a>, <V var2$56 a>)\n      set no: <r set_ctr$64 via  Set125>\n  ", "profile_text_low_explain": "\n    time         0% fanout         0 input         0 rows\n    Select (var1$54, var2$56)\n  ", "time": 0.0, "fanout": 0.0, "input_rows": 0.0, "cardinality_estimate": 0, "cardinality_fanout": 0, "operator_type": 0, "precode_bool": 0, "after_code_bool": 0, "group_by_read_bool": 0, "distinct_bool": 0, "TOP_bool": 0, "TOP_num": 0, "top_order_by_bool": 0, "skip_node_bool": 0, "skip_node_num": 0, "{": 0, "}": 0, "select?": 1, "start_optional": 0, "end_optional": 0, "IRI_ID\"...direct/P31\"": 0, "IRI_ID\"...direct/P625\"": 0, "optional_section?": 0, "after_test_1op?": 0, "after_test_lvl": 0, "target_bracket": 0, "transitive_bracket": 0, "union_sort_lvl": 0, "sort_lvl": 0, "subquerie_lvl": 0, "union_sub_lvl": 0, "subquery_select?": 0}, "GENERAL_FEATURES": {"LIMIT": 0, "precompiled": {"ql_rt_msec": "0", "ql_rt_clocks": "2%", "ql_rnd_rows": "1", "ql_seq_rows": "0", "ql_same_seg": "0%", "ql_same_page": "0%", "ql_disk_reads": "0", "ql_spec_disk_reads": "0", "ql_cl_wait_clocks": "0"}, "compiled": {"ql_c_msec": "2", "ql_c_disk": "0", "ql_c_clocks": "0%", "ql_cl_messages": "0", "ql_c_cl_wait": "0%"}}}